aio_dprcon/__init__.py
aio_dprcon/cli.py
aio_dprcon/client.py
aio_dprcon/config.py
aio_dprcon/exceptions.py
aio_dprcon/parser.py
aio_dprcon/protocol.py
aio_dprcon/shell.py
aio_dprcon-0.1.5.dist-info/DESCRIPTION.rst
aio_dprcon-0.1.5.dist-info/METADATA
aio_dprcon-0.1.5.dist-info/RECORD
aio_dprcon-0.1.5.dist-info/WHEEL
aio_dprcon-0.1.5.dist-info/entry_points.txt
aio_dprcon-0.1.5.dist-info/metadata.json
aio_dprcon-0.1.5.dist-info/top_level.txt
tests/__init__.py
tests/conftest.py
tests/test_client.py
tests/test_protocol.py
